petstore_vinclient_ti/__init__.py
petstore_vinclient_ti/api_client.py
petstore_vinclient_ti/api_response.py
petstore_vinclient_ti/configuration.py
petstore_vinclient_ti/exceptions.py
petstore_vinclient_ti/py.typed
petstore_vinclient_ti/rest.py
petstore_vinclient_ti/api/__init__.py
petstore_vinclient_ti/api/pet_api.py
petstore_vinclient_ti/api/store_api.py
petstore_vinclient_ti/api/user_api.py
petstore_vinclient_ti/models/__init__.py
petstore_vinclient_ti/models/address.py
petstore_vinclient_ti/models/api_response.py
petstore_vinclient_ti/models/category.py
petstore_vinclient_ti/models/customer.py
petstore_vinclient_ti/models/order.py
petstore_vinclient_ti/models/pet.py
petstore_vinclient_ti/models/tag.py
petstore_vinclient_ti/models/user.py
petstore_vinclient_ti-0.0.1.dist-info/METADATA
petstore_vinclient_ti-0.0.1.dist-info/WHEEL
petstore_vinclient_ti-0.0.1.dist-info/top_level.txt
petstore_vinclient_ti-0.0.1.dist-info/RECORD
